makecli/__init__.py
makecli/cli.py
makecli/makecli.py
makecli/run.py
makecli/template.py
makecli-0.0.11.dist-info/DESCRIPTION.rst
makecli-0.0.11.dist-info/METADATA
makecli-0.0.11.dist-info/RECORD
makecli-0.0.11.dist-info/WHEEL
makecli-0.0.11.dist-info/entry_points.txt
makecli-0.0.11.dist-info/metadata.json
makecli-0.0.11.dist-info/top_level.txt
